setup.cfg
setup.py
redis_orm.egg-info/PKG-INFO
redis_orm.egg-info/SOURCES.txt
redis_orm.egg-info/dependency_links.txt
redis_orm.egg-info/requires.txt
redis_orm.egg-info/top_level.txt
redisorm/__init__.py
redisorm/core.py
redisorm/types.py