Metadata-Version: 1.0
Name: redis-orm
Version: 0.4.1
Summary: Redis object relation mapper
Home-page: UNKNOWN
Author: minamorl
Author-email: minamorl@minamorl.com
License: UNKNOWN
Platform: UNKNOWN
